[{"style": "Saison", "recipe_count": 3134, "fermentables": {"recipe_count": 1315, "grain_usage": [{"slug": "weyermann-caramunich-i", "stats": {"min": 0, "max": 14.798148039714214, "mean": 6.037321672373965, "median": 4.53857791225416, "std": 4.380413183670124}, "usage": {"min": 0, "max": 15}, "recipe_count": 55}, {"slug": "briess-caramel-malt-60l", "stats": {"min": 0, "max": 11.365293307825713, "mean": 5.190395111405611, "median": 4.675000083668769, "std": 3.0874490982100515}, "usage": {"min": 0, "max": 11}, "recipe_count": 62}, {"slug": "briess-black-malt", "stats": {"min": 0, "max": 1.4766611737750233, "mean": 0.5363150314265553, "median": 0.39198105616479295, "std": 0.470173071174234}, "usage": {"min": 0, "max": 1}, "recipe_count": 10}, {"slug": "weyermann-pale-wheat-malt", "stats": {"min": 0, "max": 33.54078610983785, "mean": 14.550707712012626, "median": 11.911514463981849, "std": 9.495039198912615}, "usage": {"min": 0, "max": 34}, "recipe_count": 98}, {"slug": "generic-pale-chocolate-malt", "stats": {"min": 0.5924640695387267, "max": 4.32205606052038, "mean": 2.457260065029553, "median": 2.7240143369175627, "std": 0.9323979977454132}, "usage": {"min": 1, "max": 4}, "recipe_count": 4}, {"slug": "weyermann-carafa-special-iii", "stats": {"min": 0, "max": 2.2712072780564223, "mean": 0.9133243624905695, "median": 0.695682420974825, "std": 0.6789414577829264}, "usage": {"min": 0, "max": 2}, "recipe_count": 6}, {"slug": "weyermann-munich-malt-ii", "stats": {"min": 0, "max": 24.696377734343805, "mean": 10.674108349711071, "median": 8.333333333333332, "std": 7.011134692316367}, "usage": {"min": 0, "max": 25}, "recipe_count": 29}, {"slug": "generic-6-row-brewers-malt", "stats": {"min": 0, "max": 77.65623128211757, "mean": 33.177653176868596, "median": 31.174089068825907, "std": 22.23928905262449}, "usage": {"min": 0, "max": 78}, "recipe_count": 22}, {"slug": "generic-molasses", "stats": {"min": 0.05125576627370577, "max": 0.05125576627370577, "mean": 0.05125576627370577, "median": 0.05125576627370577, "std": 0.0}, "usage": {"min": 0, "max": 0}, "recipe_count": 1}, {"slug": "briess-caramel-malt-90l", "stats": {"min": 4.347826086956521, "max": 4.347826086956521, "mean": 4.347826086956521, "median": 4.347826086956521, "std": 0.0}, "usage": {"min": 4, "max": 4}, "recipe_count": 1}, {"slug": "weyermann-melanoidin-malt", "stats": {"min": 0, "max": 12.178715983156717, "mean": 5.4366008836590805, "median": 4.761904761904761, "std": 3.371057549748818}, "usage": {"min": 0, "max": 12}, "recipe_count": 73}, {"slug": "briess-wheat-malt-red", "stats": {"min": 0, "max": 31.74963691171198, "mean": 12.951118325313328, "median": 10.0, "std": 9.399259293199327}, "usage": {"min": 0, "max": 32}, "recipe_count": 268}, {"slug": "briess-brewers-oat-flakes", "stats": {"min": 0, "max": 14.730255100122562, "mean": 6.843990181107719, "median": 5.263157894736841, "std": 3.9431324595074213}, "usage": {"min": 0, "max": 15}, "recipe_count": 184}, {"slug": "weyermann-caraaroma", "stats": {"min": 0, "max": 7.340848468439977, "mean": 3.314624628642054, "median": 3.242128935532234, "std": 2.0131119198989613}, "usage": {"min": 0, "max": 7}, "recipe_count": 4}, {"slug": "briess-brewers-rye-flakes", "stats": {"min": 0, "max": 19.43501985109166, "mean": 9.278322474930967, "median": 8.055142586836059, "std": 5.0783486880803475}, "usage": {"min": 0, "max": 19}, "recipe_count": 62}, {"slug": "generic-dextrose-corn-sugar", "stats": {"min": 1.9980002507636447, "max": 12.241171198413358, "mean": 7.119585724588501, "median": 7.373428474345904, "std": 2.560792736912428}, "usage": {"min": 2, "max": 12}, "recipe_count": 66}, {"slug": "weyermann-caramunich-ii", "stats": {"min": 0, "max": 9.97247376453036, "mean": 4.426018275497623, "median": 4.040404040583991, "std": 2.773227744516369}, "usage": {"min": 0, "max": 10}, "recipe_count": 103}, {"slug": "generic-brown-sugar-dark", "stats": {"min": 2.3848678785042097, "max": 2.6248841324389867, "mean": 2.504876005471598, "median": 2.4725274725274726, "std": 0.06000406348369416}, "usage": {"min": 2, "max": 3}, "recipe_count": 4}, {"slug": "weyermann-carared", "stats": {"min": 0, "max": 12.254332464486765, "mean": 5.929398392708349, "median": 5.0, "std": 3.162467035889208}, "usage": {"min": 0, "max": 12}, "recipe_count": 9}, {"slug": "weyermann-carahell", "stats": {"min": 0, "max": 21.932497149648285, "mean": 8.061554256054736, "median": 5.484167049105094, "std": 6.9354714467967735}, "usage": {"min": 0, "max": 22}, "recipe_count": 33}, {"slug": "briess-brewers-barley-flakes", "stats": {"min": 0, "max": 10.943539243604068, "mean": 5.097879365833083, "median": 3.964757709251101, "std": 2.9228299388854926}, "usage": {"min": 0, "max": 11}, "recipe_count": 17}, {"slug": "briess-pilsen-malt", "stats": {"min": 27.084622351117183, "max": 103.774560380917, "mean": 65.42959136601709, "median": 70.83333333333333, "std": 19.172484507449955}, "usage": {"min": 27, "max": 100}, "recipe_count": 87}, {"slug": "briess-wheat-malt-white", "stats": {"min": 0, "max": 34.054030445114826, "mean": 13.908655841136467, "median": 11.11111111111111, "std": 10.07268730198918}, "usage": {"min": 0, "max": 34}, "recipe_count": 475}, {"slug": "generic-brown-sugar-light", "stats": {"min": 1.821135510643681, "max": 16.08682932155886, "mean": 8.95398241610127, "median": 8.571428571644534, "std": 3.566423452728795}, "usage": {"min": 2, "max": 16}, "recipe_count": 15}, {"slug": "briess-caramel-malt-20l", "stats": {"min": 0, "max": 16.67401060489405, "mean": 6.662609284012847, "median": 5.027932960893855, "std": 5.005700660440601}, "usage": {"min": 0, "max": 17}, "recipe_count": 75}, {"slug": "weyermann-carafa-special-i", "stats": {"min": 0.4975124373743971, "max": 0.4975124373743971, "mean": 0.4975124373743971, "median": 0.4975124373743971, "std": 0.0}, "usage": {"min": 0, "max": 0}, "recipe_count": 2}, {"slug": "weyermann-vienna-malt", "stats": {"min": 0, "max": 55.1681890726815, "mean": 20.038813069813184, "median": 14.728682170542637, "std": 17.564688001434156}, "usage": {"min": 0, "max": 55}, "recipe_count": 273}, {"slug": "briess-caramel-malt-30l", "stats": {"min": 1.684570305177457, "max": 9.515956670573164, "mean": 5.600263487875311, "median": 5.486978774650007, "std": 1.957846591348927}, "usage": {"min": 2, "max": 10}, "recipe_count": 20}, {"slug": "generic-candi-sugar-clear", "stats": {"min": 2.3531838553085693, "max": 13.436763293557682, "mean": 7.894973574433125, "median": 7.6923076923076925, "std": 2.770894859562278}, "usage": {"min": 2, "max": 13}, "recipe_count": 17}, {"slug": "weyermann-munich-malt-i", "stats": {"min": 0, "max": 35.66689629345447, "mean": 12.927554235408023, "median": 8.955223880597012, "std": 11.369671029023225}, "usage": {"min": 0, "max": 36}, "recipe_count": 221}, {"slug": "weyermann-beech-smoked-barley-malt", "stats": {"min": 0, "max": 107.52523621840656, "mean": 39.26595949855353, "median": 29.411764705882348, "std": 34.12963835992652}, "usage": {"min": 0, "max": 100}, "recipe_count": 5}, {"slug": "weyermann-carapils", "stats": {"min": 0, "max": 12.86717853457916, "mean": 6.111562499920136, "median": 5.05050505050505, "std": 3.377808017329512}, "usage": {"min": 0, "max": 13}, "recipe_count": 31}, {"slug": "generic-honey", "stats": {"min": 0, "max": 15.78219546528672, "mean": 7.719464826384237, "median": 8.0, "std": 4.031365319451241}, "usage": {"min": 0, "max": 16}, "recipe_count": 92}, {"slug": "generic-golden-promise", "stats": {"min": 0, "max": 117.38487924229062, "mean": 54.86345946715201, "median": 67.9231337767923, "std": 31.260709887569302}, "usage": {"min": 0, "max": 100}, "recipe_count": 16}, {"slug": "generic-lactose-milk-sugar", "stats": {"min": 4.5701357466063355, "max": 4.751131221719457, "mean": 4.660633484162896, "median": 4.660633484162896, "std": 0.04524886877828038}, "usage": {"min": 5, "max": 5}, "recipe_count": 2}, {"slug": "briess-caramel-malt-40l", "stats": {"min": 0, "max": 12.849632304945604, "mean": 5.965093842796039, "median": 4.761904761904761, "std": 3.442269231074783}, "usage": {"min": 0, "max": 13}, "recipe_count": 31}, {"slug": "weyermann-caramunich-iii", "stats": {"min": 0, "max": 11.120849708509205, "mean": 4.223094133856069, "median": 3.669724770642202, "std": 3.4488777873265684}, "usage": {"min": 0, "max": 11}, "recipe_count": 25}, {"slug": "briess-carapils-malt", "stats": {"min": 0, "max": 11.975070731366529, "mean": 5.658731496468944, "median": 4.651162790697674, "std": 3.158169617448793}, "usage": {"min": 0, "max": 12}, "recipe_count": 91}, {"slug": "generic-brown-malt", "stats": {"min": 0, "max": 8.592291389750638, "mean": 3.9261223304035324, "median": 2.5817555915858468, "std": 2.3330845296735534}, "usage": {"min": 0, "max": 9}, "recipe_count": 5}, {"slug": "briess-brewers-red-wheat-flakes", "stats": {"min": 0, "max": 21.651634945095374, "mean": 9.269054979428176, "median": 8.333333333333332, "std": 6.191289982833599}, "usage": {"min": 0, "max": 22}, "recipe_count": 155}, {"slug": "generic-special-b", "stats": {"min": 0, "max": 6.207050881274343, "mean": 3.0170951084653552, "median": 2.53807106380846, "std": 1.594977886404494}, "usage": {"min": 0, "max": 6}, "recipe_count": 47}, {"slug": "generic-turbinado", "stats": {"min": 1.6833205231786534, "max": 11.492197293745313, "mean": 6.587758908461983, "median": 6.666666666666667, "std": 2.4522191926416648}, "usage": {"min": 2, "max": 11}, "recipe_count": 51}, {"slug": "briess-victory-malt", "stats": {"min": 0, "max": 15.79511106612028, "mean": 6.418215987797662, "median": 4.84866294446077, "std": 4.6884475391613085}, "usage": {"min": 0, "max": 16}, "recipe_count": 88}, {"slug": "generic-amber-malt", "stats": {"min": 0, "max": 11.808227808448734, "mean": 4.969255843569127, "median": 4.545454545454546, "std": 3.419485982439803}, "usage": {"min": 0, "max": 12}, "recipe_count": 9}, {"slug": "briess-roasted-barley", "stats": {"min": 0, "max": 2.4202997915467916, "mean": 1.0500984937656825, "median": 0.9009009009009009, "std": 0.6851006488905546}, "usage": {"min": 0, "max": 2}, "recipe_count": 15}, {"slug": "briess-munich-malt-20l", "stats": {"min": 0, "max": 18.244328006518415, "mean": 7.810585702251657, "median": 6.155303030303029, "std": 5.216871152133378}, "usage": {"min": 0, "max": 18}, "recipe_count": 96}, {"slug": "gambrinus-honey-malt", "stats": {"min": 0, "max": 13.488092569433807, "mean": 5.996117030989032, "median": 5.0, "std": 3.745987769222388}, "usage": {"min": 0, "max": 13}, "recipe_count": 66}, {"slug": "briess-chocolate-malt", "stats": {"min": 1.1738261738261742, "max": 2.5391275391275396, "mean": 1.8564768564768568, "median": 1.8564768564768568, "std": 0.3413253413253413}, "usage": {"min": 1, "max": 3}, "recipe_count": 2}, {"slug": "briess-rye-malt", "stats": {"min": 0, "max": 31.54423443751645, "mean": 14.542927009276712, "median": 14.285714285714285, "std": 8.50065371411987}, "usage": {"min": 0, "max": 32}, "recipe_count": 183}, {"slug": "weyermann-carafa-special-ii", "stats": {"min": 0.37647661604352084, "max": 0.9073090265904546, "mean": 0.6418928213169878, "median": 0.6896551724137931, "std": 0.13270810263673347}, "usage": {"min": 0, "max": 1}, "recipe_count": 3}, {"slug": "generic-sucrose-table-sugar", "stats": {"min": 1.1017929698410542, "max": 13.39140776662984, "mean": 7.246600368235447, "median": 7.575757575757576, "std": 3.0724036991971966}, "usage": {"min": 1, "max": 13}, "recipe_count": 123}, {"slug": "briess-caramel-malt-80l", "stats": {"min": 1.3097847735644799, "max": 4.948125720145002, "mean": 3.128955246854741, "median": 3.0266388186581654, "std": 0.9095852366451306}, "usage": {"min": 1, "max": 5}, "recipe_count": 12}, {"slug": "generic-flaked-rice", "stats": {"min": 0, "max": 19.194997186815506, "mean": 8.45125513136576, "median": 7.999999999999999, "std": 5.371871027724873}, "usage": {"min": 0, "max": 19}, "recipe_count": 10}, {"slug": "weyermann-pilsner-malt", "stats": {"min": 30.29153981177287, "max": 102.46445638584032, "mean": 66.3779980988066, "median": 70.37037037037037, "std": 18.043229143516864}, "usage": {"min": 30, "max": 100}, "recipe_count": 771}, {"slug": "briess-brewers-malt", "stats": {"min": 16.062192451338433, "max": 106.09189993416736, "mean": 61.077046192752896, "median": 66.66666666666667, "std": 22.50742687070723}, "usage": {"min": 16, "max": 100}, "recipe_count": 401}, {"slug": "briess-smoked-malt-mesquite", "stats": {"min": 6.392052697607116, "max": 9.10522511851128, "mean": 7.748638908059198, "median": 7.407407407407408, "std": 0.6782931052260411}, "usage": {"min": 6, "max": 9}, "recipe_count": 3}, {"slug": "briess-goldpils-vienna-malt", "stats": {"min": 0, "max": 36.752161117141796, "mean": 14.322750027258902, "median": 10.49191606467148, "std": 11.214705544941447}, "usage": {"min": 0, "max": 37}, "recipe_count": 30}, {"slug": "briess-pale-ale-malt", "stats": {"min": 9.078138418967434, "max": 112.87444855419875, "mean": 60.976293486583096, "median": 67.79661016949152, "std": 25.94907753380783}, "usage": {"min": 9, "max": 100}, "recipe_count": 159}, {"slug": "briess-caramel-vienne-malt-20l", "stats": {"min": 0, "max": 25.12124254248456, "mean": 8.31290915107605, "median": 6.0, "std": 8.404166695704255}, "usage": {"min": 0, "max": 25}, "recipe_count": 41}, {"slug": "briess-brewers-yellow-corn-flakes", "stats": {"min": 0, "max": 25.594286651018713, "mean": 12.670650077172828, "median": 12.903225806451616, "std": 6.461818286922942}, "usage": {"min": 0, "max": 26}, "recipe_count": 51}, {"slug": "briess-munich-malt-10l", "stats": {"min": 0, "max": 24.930611182810495, "mean": 11.41681238916117, "median": 9.876543209876543, "std": 6.756899396824663}, "usage": {"min": 0, "max": 25}, "recipe_count": 143}, {"slug": "briess-dark-chocolate-malt", "stats": {"min": 0, "max": 2.7123308508886734, "mean": 1.3030435938330678, "median": 1.3454545454545455, "std": 0.7046436285278028}, "usage": {"min": 0, "max": 3}, "recipe_count": 4}, {"slug": "briess-caramel-malt-10l", "stats": {"min": 0, "max": 21.026891422481462, "mean": 7.4786110191196, "median": 4.761904761904761, "std": 6.774140201680931}, "usage": {"min": 0, "max": 21}, "recipe_count": 37}], "unique_fermentables": 4, "category_usage": [{"name": "base", "stats": {"min": 46.61367324849341, "max": 103.29497977192683, "mean": 74.95432651021012, "median": 77.22772277699725, "std": 14.170326630858355}, "usage": {"min": 47, "max": 100}, "unique_fermentables": 1, "recipe_count": 1310}, {"name": "munich", "stats": {"min": 0, "max": 20.12694641298644, "mean": 4.219740705120152, "median": 0.0, "std": 7.953602853933144}, "usage": {"min": 0, "max": 20}, "unique_fermentables": 1, "recipe_count": 469}, {"name": "crystal", "stats": {"min": 0, "max": 11.47258787099432, "mean": 2.2844264990456473, "median": 0.0, "std": 4.594080685974336}, "usage": {"min": 0, "max": 11}, "unique_fermentables": 1, "recipe_count": 462}, {"name": "roasted", "stats": {"min": 0, "max": 0.5413380080995216, "mean": 0.03670680272456134, "median": 0.0, "std": 0.2523156026874801}, "usage": {"min": 0, "max": 1}, "unique_fermentables": 1, "recipe_count": 44}, {"name": "specialty", "stats": {"min": 0, "max": 9.25887071120386, "mean": 1.7246988467656224, "median": 0.0, "std": 3.767085932219119}, "usage": {"min": 0, "max": 9}, "unique_fermentables": 1, "recipe_count": 352}, {"name": "flakes and adjuncts", "stats": {"min": 0, "max": 13.800877442062601, "mean": 2.671769862816595, "median": 0.0, "std": 5.5645537896230035}, "usage": {"min": 0, "max": 14}, "unique_fermentables": 1, "recipe_count": 360}, {"name": "sugar", "stats": {"min": 0, "max": 9.629827143295026, "mean": 2.04966333478181, "median": 0.0, "std": 3.790081904256608}, "usage": {"min": 0, "max": 10}, "unique_fermentables": 1, "recipe_count": 364}, {"name": "rye", "stats": {"min": 0, "max": 15.338814942435121, "mean": 2.4613016244436183, "median": 0.0, "std": 6.438756658995752}, "usage": {"min": 0, "max": 15}, "unique_fermentables": 1, "recipe_count": 231}, {"name": "wheat", "stats": {"min": 0, "max": 29.961767008903806, "mean": 8.747893985932341, "median": 6.25, "std": 10.606936511485731}, "usage": {"min": 0, "max": 30}, "unique_fermentables": 1, "recipe_count": 811}, {"name": "smoked", "stats": {"min": 0, "max": 6.617274189702571, "mean": 0.16697772944254388, "median": 0.0, "std": 3.2251482301300136}, "usage": {"min": 0, "max": 7}, "unique_fermentables": 1, "recipe_count": 8}], "sensory_data": [{"name": "sweet", "min": 2.165, "max": 3.325, "stats": {"min": 2.1647870856771156, "max": 3.3248398430126844, "mean": 2.7448134643449, "median": 2.7333333333333334, "std": 0.2900131893338923}}, {"name": "malty", "min": 1.189, "max": 3.006, "stats": {"min": 1.1889093705591993, "max": 3.0055965538626213, "mean": 2.09725296221091, "median": 1.9866666666666666, "std": 0.45417179582585543}}, {"name": "bready", "min": 0, "max": 1.843, "stats": {"min": 0, "max": 1.8432604378185569, "mean": 0.8003035235270483, "median": 0.672340425531915, "std": 0.5214784571457544}}, {"name": "honey", "min": 0.073, "max": 2.182, "stats": {"min": 0.07319522082285745, "max": 2.181698272009194, "mean": 1.1274467464160258, "median": 1.2999999999999998, "std": 0.5271257627965842}}, {"name": "biscuit", "min": 0.625, "max": 1.207, "stats": {"min": 0.6251024877183666, "max": 1.2074410097316373, "mean": 0.9162717487250019, "median": 0.9111111111111112, "std": 0.14558463050331766}}, {"name": "nutty", "min": 0, "max": 1.129, "stats": {"min": 0, "max": 1.1294274994891436, "mean": 0.36422917347060646, "median": 0.16666666666666663, "std": 0.3825991630092685}}, {"name": "toast", "min": 0, "max": 1.397, "stats": {"min": 0, "max": 1.3971017087892872, "mean": 0.4542236983892594, "median": 0.2857142857142857, "std": 0.4714390052000139}}, {"name": "grainy", "min": 0, "max": 2.174, "stats": {"min": 0, "max": 2.1741951881829955, "mean": 0.8013221138139673, "median": 0.5599999999999999, "std": 0.686436537184514}}, {"name": "bitter", "min": 0, "max": 0.173, "stats": {"min": 0, "max": 0.1733975754824802, "mean": 0.03701687615548679, "median": 0.0, "std": 0.0681903496634967}}, {"name": "coffee", "min": 0, "max": 0.168, "stats": {"min": 0, "max": 0.1677438298246155, "mean": 0.03748752064104334, "median": 0.010909090909090908, "std": 0.06512815459178609}}, {"name": "cocoa", "min": 0, "max": 0.235, "stats": {"min": 0, "max": 0.23478194974906397, "mean": 0.05898166733413553, "median": 0.023255813953488372, "std": 0.08790014120746421}}, {"name": "dark_chocolate", "min": 0, "max": 0.158, "stats": {"min": 0, "max": 0.1575135369096197, "mean": 0.037080454173444, "median": 0.01, "std": 0.06021654136808784}}, {"name": "roasted_almond", "min": 0, "max": 0.259, "stats": {"min": 0, "max": 0.2588976915022457, "mean": 0.06686709208250215, "median": 0.031683168316831684, "std": 0.09601529970987177}}, {"name": "dried_fruit", "min": 0, "max": 0.237, "stats": {"min": 0, "max": 0.23683633303253843, "mean": 0.06190012230115191, "median": 0.03, "std": 0.08746810536569326}}, {"name": "wood_smoke", "min": 0, "max": 0.231, "stats": {"min": 0, "max": 0.23083087856022438, "mean": 0.02581410947829075, "median": 0.0076883649410558665, "std": 0.10250838454096682}}, {"name": "clove", "min": 0, "max": 0.329, "stats": {"min": 0, "max": 0.32873703631381784, "mean": 0.07266418937523389, "median": 0.016666666666666666, "std": 0.12803642346929198}}, {"name": "almond", "min": 0, "max": 0.755, "stats": {"min": 0, "max": 0.7552329449719621, "mean": 0.2665165763911664, "median": 0.23999999991957532, "std": 0.24435818429039788}}, {"name": "hazelnut", "min": 0, "max": 1.008, "stats": {"min": 0, "max": 1.007949542058871, "mean": 0.37791361726001166, "median": 0.41111111111111104, "std": 0.3150179623994297}}, {"name": "raisin", "min": 0, "max": 0.483, "stats": {"min": 0, "max": 0.48331047794827486, "mean": 0.1853269875623487, "median": 0.16410256410256407, "std": 0.14899174519296307}}, {"name": "vanilla", "min": 0, "max": 0.636, "stats": {"min": 0, "max": 0.6363555355243898, "mean": 0.248002865112216, "median": 0.2789189189189189, "std": 0.1941763352060869}}, {"name": "marmalade", "min": 0, "max": 0.39, "stats": {"min": 0, "max": 0.3896799341915608, "mean": 0.1445923316299901, "median": 0.1473684210526316, "std": 0.12254380128078533}}, {"name": "toffee", "min": 0, "max": 0.82, "stats": {"min": 0, "max": 0.8198210694972283, "mean": 0.3189494516856399, "median": 0.3095022624434389, "std": 0.2504358089057942}}, {"name": "caramel", "min": 0, "max": 1.046, "stats": {"min": 0, "max": 1.04628288950859, "mean": 0.42525461346344023, "median": 0.44943820224719094, "std": 0.3105141380225749}}, {"name": "dark_caramel", "min": 0, "max": 0.302, "stats": {"min": 0, "max": 0.301626167013053, "mean": 0.0780649200240806, "median": 0.03225806448921168, "std": 0.11178062349448621}}, {"name": "sour", "min": 0, "max": 0.76, "stats": {"min": 0, "max": 0.7601061966940816, "mean": 0.29317158462004356, "median": 0.3555555555555555, "std": 0.23346730603701907}}, {"name": "graham_cracker", "min": 0, "max": 1.4, "stats": {"min": 0, "max": 1.3998541052731146, "mean": 0.39363466601607416, "median": 0.1, "std": 0.5031097196285202}}, {"name": "wheat_flour", "min": 0, "max": 0.595, "stats": {"min": 0, "max": 0.5954000951006366, "mean": 0.17512113699673248, "median": 0.13333333333333328, "std": 0.21013947905195207}}, {"name": "bread_dough", "min": 0, "max": 0.791, "stats": {"min": 0, "max": 0.7909095539665663, "mean": 0.22536152881832808, "median": 0.1595744680851064, "std": 0.2827740125741191}}, {"name": "sourdough", "min": 0, "max": 0.062, "stats": {"min": 0, "max": 0.06234888822329263, "mean": 0.00897299827219411, "median": 0.0, "std": 0.02668794497554926}}, {"name": "roasted_marshmallow", "min": 0, "max": 0.066, "stats": {"min": 0, "max": 0.06589717858341139, "mean": 0.007470931268043288, "median": 0.0, "std": 0.02921312365768405}}, {"name": "burnt_sugar", "min": 0, "max": 0.068, "stats": {"min": 0, "max": 0.06794904845545244, "mean": 0.00793880883991577, "median": 0.0, "std": 0.03000511980776833}}, {"name": "prune", "min": 0, "max": 0.038, "stats": {"min": 0, "max": 0.03805266976189995, "mean": 0.0041719976812398364, "median": 0.0, "std": 0.016940336040330056}}, {"name": "raisin_bread", "min": 0, "max": 0, "stats": {"min": 0, "max": 0, "mean": 0, "median": 0, "std": 0}}, {"name": "woody", "min": 0, "max": 0, "stats": {"min": 0, "max": 0, "mean": 0, "median": 0, "std": 0}}, {"name": "dark_toast", "min": 0, "max": 0, "stats": {"min": 0, "max": 0, "mean": 0, "median": 0, "std": 0}}, {"name": "bread_crust", "min": 0, "max": 0.146, "stats": {"min": 0, "max": 0.14610845641626935, "mean": 0.018298736054543432, "median": 0.0, "std": 0.06390486018086296}}, {"name": "earthy", "min": 0, "max": 0.3, "stats": {"min": 0, "max": 0.3067762988487024, "mean": 0.04922603248887237, "median": 0.0, "std": 0.128775133179915}}, {"name": "rye_bready", "min": 0, "max": 0.3, "stats": {"min": 0, "max": 0.3067762988487024, "mean": 0.04922603248887237, "median": 0.0, "std": 0.128775133179915}}, {"name": "roasted", "min": 0, "max": 0.013, "stats": {"min": 0, "max": 0.013483832479465075, "mean": 0.000834808729637618, "median": 0.0, "std": 0.006324511874913728}}, {"name": "burnt", "min": 0, "max": 0.009, "stats": {"min": 0, "max": 0.008531557340080253, "mean": 0.0005316239686554506, "median": 0.0, "std": 0.003999966685712401}}, {"name": "milk_chocolate", "min": 0, "max": 0.006, "stats": {"min": 0, "max": 0.0064033864425288075, "mean": 0.00021736280310663433, "median": 0.0, "std": 0.0030930118197110864}}, {"name": "tobacco", "min": 0, "max": 0, "stats": {"min": 0, "max": 0, "mean": 0, "median": 0, "std": 0}}, {"name": "molasses", "min": 0, "max": 0.038, "stats": {"min": 0, "max": 0.038465024466886114, "mean": 0.0038068458666928352, "median": 0.0, "std": 0.01732908930009664}}, {"name": "creamy", "min": 0, "max": 0.007, "stats": {"min": 0, "max": 0.007406959528773781, "mean": 0.000141768318909898, "median": 0.0, "std": 0.0036325956049319415}}, {"name": "pretzel", "min": 0, "max": 0.119, "stats": {"min": 0, "max": 0.11938764561884367, "mean": 0.01053310292135716, "median": 0.0, "std": 0.054427271348743256}}, {"name": "tart", "min": 0, "max": 0.068, "stats": {"min": 0, "max": 0.06822151178219638, "mean": 0.006018915955061234, "median": 0.0, "std": 0.031101297913567572}}, {"name": "ash", "min": 0, "max": 0.015, "stats": {"min": 0, "max": 0.015197469263229138, "mean": 0.000353550064246047, "median": 0.0, "std": 0.0074219595994915455}}, {"name": "barbeque", "min": 0, "max": 0.03, "stats": {"min": 0, "max": 0.030394938526458276, "mean": 0.000707100128492094, "median": 0.0, "std": 0.014843919198983091}}]}, "hops": {"recipe_count": 1642, "recipe": {"ibu": {"min": 0, "max": 75.50073987327383, "mean": 35.23958929596753, "median": 30.04477633639479, "std": 20.130575288653148}, "amount": {"min": 0.3574606064135333, "max": 7.092242610690166, "mean": 3.7248516085518495, "median": 3.509078049776265, "std": 1.683695501069158}, "unique_hops": 2, "flavor": {"total": {"min": 0, "max": 22.247098195461152, "mean": 6.114339303545133, "median": 2.8435988891423625, "std": 8.06637944595801}, "descriptors": {"Citrus": {"min": 0, "max": 5.6088652531998235, "mean": 1.1419611258629028, "median": 0.3790690805103416, "std": 2.2334520636684605, "recipe_count": 402}, "Grapefruit": {"min": 0, "max": 5.416560545884218, "mean": 1.6787084265073293, "median": 1.0357901409835648, "std": 1.8689260596884443, "recipe_count": 422}, "Orange": {"min": 0, "max": 4.168023862810241, "mean": 1.2631199483617876, "median": 0.6571987450175114, "std": 1.4524519572242265, "recipe_count": 255}, "Lemon": {"min": 0, "max": 4.679731775413295, "mean": 1.1998822111207825, "median": 0.5092248665889362, "std": 1.739924782146256, "recipe_count": 580}, "Melon": {"min": 0, "max": 5.694733905820618, "mean": 2.0923317120243783, "median": 1.7700510838919796, "std": 1.8012010968981198, "recipe_count": 247}, "Apricot": {"min": 0, "max": 4.787626462867073, "mean": 1.7008240251243423, "median": 1.2658362296998362, "std": 1.5434012188713655, "recipe_count": 166}, "Peach": {"min": 0, "max": 4.780470290565085, "mean": 1.7510310989918663, "median": 1.45087638757149, "std": 1.5147195957866093, "recipe_count": 157}, "Medium Intense": {"min": 0, "max": 3.613229493641923, "mean": 0.8499976696177606, "median": 0.3639088215961417, "std": 1.3816159120120812, "recipe_count": 174}, "Floral": {"min": 0, "max": 2.8162699222975283, "mean": 0.7622040969254699, "median": 0.42186423169850373, "std": 1.0270329126860291, "recipe_count": 1090}, "Spicy": {"min": 0, "max": 2.47576117150683, "mean": 0.5934585446267643, "median": 0.26885348866216796, "std": 0.9411513134400329, "recipe_count": 696}, "Lime": {"min": 0, "max": 6.850647760996475, "mean": 2.2668271565350473, "median": 1.720311525140867, "std": 2.291910302230714, "recipe_count": 214}, "Gooseberry": {"min": 0, "max": 5.8123980293357835, "mean": 1.92913744678801, "median": 1.438674739485187, "std": 1.9416302912738868, "recipe_count": 187}, "Passion Fruit": {"min": 0, "max": 8.201867372696068, "mean": 2.250226959418608, "median": 1.2417715271590914, "std": 2.97582020663873, "recipe_count": 183}, "Earthy": {"min": 0, "max": 2.5044584614727885, "mean": 0.6719408202658907, "median": 0.39770140351113903, "std": 0.9162588206034488, "recipe_count": 881}, "Mild": {"min": 0, "max": 2.4389105769360055, "mean": 0.6465706316758375, "median": 0.36674796161965373, "std": 0.8961699726300841, "recipe_count": 627}, "Noble": {"min": 0, "max": 2.8421993672849397, "mean": 0.606087780358679, "median": 0.22328052758511815, "std": 1.1180557934631303, "recipe_count": 235}, "Herbal": {"min": 0, "max": 2.639122684277493, "mean": 0.6953302318902669, "median": 0.4095163200136638, "std": 0.971896226193613, "recipe_count": 655}, "Lavender": {"min": 0, "max": 2.0336215966141347, "mean": 0.4957388293540496, "median": 0.21231571572098107, "std": 0.7689413836300425, "recipe_count": 341}, "Honey": {"min": 0, "max": 2.031603447057581, "mean": 0.49595074752521706, "median": 0.21654971171584092, "std": 0.7678263497661818, "recipe_count": 342}, "Thyme": {"min": 0, "max": 2.0336215966141347, "mean": 0.4957388293540496, "median": 0.21231571572098107, "std": 0.7689413836300425, "recipe_count": 341}}}}, "additions": {"60": {"ibu": {"min": 6.752734256164494, "max": 36.116899211706496, "mean": 21.434816733935495, "median": 20.6452096453908, "std": 7.3410412388855}, "amount": {"min": 0, "max": 3.023086645067857, "mean": 1.421040738617068, "median": 1.3616628374983673, "std": 0.8010229532253946}, "unique_hops": 1, "flavor": {"total": {"min": 0, "max": 0.09633928315612049, "mean": 0.03050161740722485, "median": 0.023457118743132055, "std": 0.03291883287444782}, "descriptors": {"Citrus": {"min": 0, "max": 0.009592508894404645, "mean": 0.0013364418201005938, "median": 0.0, "std": 0.004128033537152026, "recipe_count": 237}, "Grapefruit": {"min": 0, "max": 0.010022414478281179, "mean": 0.0012563189885155496, "median": 0.0, "std": 0.0043830477448828144, "recipe_count": 211}, "Orange": {"min": 0, "max": 0.007224202856046795, "mean": 0.0007556627847352963, "median": 0.0, "std": 0.003234270035655749, "recipe_count": 119}, "Lemon": {"min": 0, "max": 0.009305053445901249, "mean": 0.001571104136719211, "median": 0.0, "std": 0.0038669746545910186, "recipe_count": 318}, "Melon": {"min": 0, "max": 0.006612831178340149, "mean": 0.0005459534653112322, "median": 0.0, "std": 0.003033438856514458, "recipe_count": 86}, "Apricot": {"min": 0, "max": 0.004063537916788744, "mean": 0.00028000426023859563, "median": 0.0, "std": 0.001891766828275074, "recipe_count": 49}, "Peach": {"min": 0, "max": 0.003984807285931865, "mean": 0.00026456797602329924, "median": 0.0, "std": 0.0018601196549542828, "recipe_count": 45}, "Medium Intense": {"min": 0, "max": 0.005724435129963102, "mean": 0.0005076450277257431, "median": 0.0, "std": 0.0026083950511186795, "recipe_count": 88}, "Floral": {"min": 0, "max": 0.016688251837537502, "mean": 0.003841565659651156, "median": 0.0, "std": 0.006423343088943174, "recipe_count": 677}, "Spicy": {"min": 0, "max": 0.012420618120782224, "mean": 0.0024922708550533805, "median": 0.0, "std": 0.004964173632864422, "recipe_count": 467}, "Lime": {"min": 0, "max": 0.006646958683519059, "mean": 0.0005920629461714773, "median": 0.0, "std": 0.003027447868673791, "recipe_count": 103}, "Gooseberry": {"min": 0, "max": 0.0053027881908297115, "mean": 0.0003580559025809241, "median": 0.0, "std": 0.0024723661441243936, "recipe_count": 77}, "Passion Fruit": {"min": 0, "max": 0.0060785896242091094, "mean": 0.00040091048512663703, "median": 0.0, "std": 0.0028388395695412363, "recipe_count": 63}, "Earthy": {"min": 0, "max": 0.013399440867587296, "mean": 0.0024528171315243655, "median": 0.0, "std": 0.005473311868031465, "recipe_count": 462}, "Mild": {"min": 0, "max": 0.010922002084365563, "mean": 0.001566236368040904, "median": 0.0, "std": 0.00467788285816233, "recipe_count": 288}, "Noble": {"min": 0, "max": 0.00907144410687068, "mean": 0.0010408215375678595, "median": 0.0, "std": 0.004015311284651411, "recipe_count": 152}, "Herbal": {"min": 0, "max": 0.01117013394641462, "mean": 0.0015988459301801497, "median": 0.0, "std": 0.0047856440081172355, "recipe_count": 282}, "Lavender": {"min": 0, "max": 0.007033023438983201, "mean": 0.0009856435206053802, "median": 0.0, "std": 0.00302368995918891, "recipe_count": 217}, "Honey": {"min": 0, "max": 0.007033023438983201, "mean": 0.0009856435206053802, "median": 0.0, "std": 0.00302368995918891, "recipe_count": 217}, "Thyme": {"min": 0, "max": 0.007033023438983201, "mean": 0.0009856435206053802, "median": 0.0, "std": 0.00302368995918891, "recipe_count": 217}}}, "recipe_count": 1484}, "45": {"ibu": {"min": 0, "max": 28.43639509139027, "mean": 13.269841817235067, "median": 11.51782632701433, "std": 7.583276637077602}, "amount": {"min": 0, "max": 2.2717441693024734, "mean": 1.0797286680867664, "median": 0.8967171574270928, "std": 0.5960077506078536}, "unique_hops": 1, "flavor": {"total": {"min": 0, "max": 0.8107520838441888, "mean": 0.24111880048356213, "median": 0.15740904378113452, "std": 0.28481664168031334}, "descriptors": {"Citrus": {"min": 0, "max": 0.062056643382418786, "mean": 0.007294711213162862, "median": 0.0, "std": 0.02738096608462796, "recipe_count": 51}, "Grapefruit": {"min": 0, "max": 0.10300996468980764, "mean": 0.01153595804439111, "median": 0.0, "std": 0.04573700332270826, "recipe_count": 55}, "Orange": {"min": 0, "max": 0.04949127261446065, "mean": 0.004546476391104754, "median": 0.0, "std": 0.02247239811167795, "recipe_count": 25}, "Lemon": {"min": 0, "max": 0.08436652504408443, "mean": 0.012390324949351748, "median": 0.0, "std": 0.03598810004736634, "recipe_count": 78}, "Melon": {"min": 0, "max": 0.0709935266006072, "mean": 0.005734052613443569, "median": 0.0, "std": 0.03262973699358182, "recipe_count": 25}, "Apricot": {"min": 0, "max": 0.024273239554250054, "mean": 0.0017997834873663375, "median": 0.0, "std": 0.011236728033441858, "recipe_count": 13}, "Peach": {"min": 0, "max": 0.02283412717963709, "mean": 0.0015714977682640319, "median": 0.0, "std": 0.01063131470568653, "recipe_count": 11}, "Medium Intense": {"min": 0, "max": 0.04320871410570413, "mean": 0.0034030326664508327, "median": 0.0, "std": 0.019902840719626648, "recipe_count": 23}, "Floral": {"min": 0, "max": 0.12966288831262815, "mean": 0.029886683741504338, "median": 0.0, "std": 0.04988810228556191, "recipe_count": 194}, "Spicy": {"min": 0, "max": 0.1032752550347274, "mean": 0.017936542832131197, "median": 0.0, "std": 0.0426693561012981, "recipe_count": 117}, "Lime": {"min": 0, "max": 0.09429928170138017, "mean": 0.009525597488996165, "median": 0.0, "std": 0.04238684210619201, "recipe_count": 37}, "Gooseberry": {"min": 0, "max": 0.06620025522638362, "mean": 0.004875682682189572, "median": 0.0, "std": 0.030662286272097022, "recipe_count": 25}, "Passion Fruit": {"min": 0, "max": 0.07744108284499587, "mean": 0.006558657725661467, "median": 0.0, "std": 0.0354412125596672, "recipe_count": 35}, "Earthy": {"min": 0, "max": 0.115611099493695, "mean": 0.021146678376742993, "median": 0.0, "std": 0.047232210558476, "recipe_count": 149}, "Mild": {"min": 0, "max": 0.09841531223973783, "mean": 0.014000422237038674, "median": 0.0, "std": 0.042207445001349576, "recipe_count": 90}, "Noble": {"min": 0, "max": 0.05941320996161721, "mean": 0.006640971780304326, "median": 0.0, "std": 0.026386119090656444, "recipe_count": 41}, "Herbal": {"min": 0, "max": 0.09574124001778166, "mean": 0.014167136112294127, "median": 0.0, "std": 0.040787051952743764, "recipe_count": 102}, "Lavender": {"min": 0, "max": 0.04329860789852671, "mean": 0.005492258807921606, "median": 0.0, "std": 0.01890317454530255, "recipe_count": 45}, "Honey": {"min": 0, "max": 0.04329860789852671, "mean": 0.005492258807921606, "median": 0.0, "std": 0.01890317454530255, "recipe_count": 45}, "Thyme": {"min": 0, "max": 0.04329860789852671, "mean": 0.005492258807921606, "median": 0.0, "std": 0.01890317454530255, "recipe_count": 45}}}, "recipe_count": 390}, "5": {"ibu": {"min": 0, "max": 13.847891272870822, "mean": 4.813669451405439, "median": 3.6259394926405886, "std": 4.517110910732691}, "amount": {"min": 0, "max": 3.4390681203924744, "mean": 1.4259963794831227, "median": 1.2875936890802469, "std": 1.0065358704546759}, "unique_hops": 1, "flavor": {"total": {"min": 0, "max": 10.90652676343362, "mean": 3.226873575843508, "median": 1.9511333536489561, "std": 3.839826593795056}, "descriptors": {"Citrus": {"min": 0, "max": 1.0238198211789475, "mean": 0.1067516779103955, "median": 0.0, "std": 0.458534071634276, "recipe_count": 67}, "Grapefruit": {"min": 0, "max": 1.4350467936025653, "mean": 0.24992721165372084, "median": 0.0, "std": 0.5925597909744222, "recipe_count": 127}, "Orange": {"min": 0, "max": 0.9567457514873586, "mean": 0.11634197240512441, "median": 0.0, "std": 0.4202018895411171, "recipe_count": 59}, "Lemon": {"min": 0, "max": 1.3697721248019874, "mean": 0.23691803851235527, "median": 0.0, "std": 0.5664270431448161, "recipe_count": 147}, "Melon": {"min": 0, "max": 1.4745280420038105, "mean": 0.21112110672555232, "median": 0.0, "std": 0.6317034676391291, "recipe_count": 89}, "Apricot": {"min": 0, "max": 0.9481897380868569, "mean": 0.11181171657394554, "median": 0.0, "std": 0.4181890107564557, "recipe_count": 55}, "Peach": {"min": 0, "max": 0.9457790356756948, "mean": 0.11017943076534578, "median": 0.0, "std": 0.4177998024551745, "recipe_count": 53}, "Medium Intense": {"min": 0, "max": 0.4517399331715125, "mean": 0.044736787807715124, "median": 0.0, "std": 0.2035015726818987, "recipe_count": 39}, "Floral": {"min": 0, "max": 1.2000872246104795, "mean": 0.25663496212159365, "median": 0.0, "std": 0.47172613124444296, "recipe_count": 244}, "Spicy": {"min": 0, "max": 0.7768853147831181, "mean": 0.1327125844469587, "median": 0.0, "std": 0.3220863651680797, "recipe_count": 138}, "Lime": {"min": 0, "max": 1.1508871473500906, "mean": 0.15099551137535622, "median": 0.0, "std": 0.49994581798736715, "recipe_count": 67}, "Gooseberry": {"min": 0, "max": 1.0024592720253676, "mean": 0.11694825492421325, "median": 0.0, "std": 0.4427555085505771, "recipe_count": 64}, "Passion Fruit": {"min": 0, "max": 1.1115666095920407, "mean": 0.12836493951576117, "median": 0.0, "std": 0.4916008350381397, "recipe_count": 49}, "Earthy": {"min": 0, "max": 1.0726373543599306, "mean": 0.19686293454391499, "median": 0.0, "std": 0.4378872099080078, "recipe_count": 195}, "Mild": {"min": 0, "max": 0.7135112846561081, "mean": 0.10511541999393217, "median": 0.0, "std": 0.304197932331088, "recipe_count": 112}, "Noble": {"min": 0, "max": 0.5312924931744395, "mean": 0.04469951182193263, "median": 0.0, "std": 0.24329649067625342, "recipe_count": 40}, "Herbal": {"min": 0, "max": 0.8545980114717489, "mean": 0.13112402865804637, "median": 0.0, "std": 0.3617369914068512, "recipe_count": 135}, "Lavender": {"min": 0, "max": 0.567033032351179, "mean": 0.06357498216843668, "median": 0.0, "std": 0.25172902509137113, "recipe_count": 66}, "Honey": {"min": 0, "max": 0.5700551854491481, "mean": 0.06467617372636947, "median": 0.0, "std": 0.25268950586138933, "recipe_count": 67}, "Thyme": {"min": 0, "max": 0.567033032351179, "mean": 0.06357498216843668, "median": 0.0, "std": 0.25172902509137113, "recipe_count": 66}}}, "recipe_count": 516}, "flameout": {"ibu": {"min": 0, "max": 0, "mean": 0, "median": 0, "std": 0}, "amount": {"min": 0, "max": 3.473991843686404, "mean": 1.5210026562093273, "median": 1.3616639470209884, "std": 0.9764945937385385}, "unique_hops": 1, "flavor": {"total": {"min": 0, "max": 19.41568095803683, "mean": 6.5162128588418335, "median": 4.267484986842537, "std": 6.449734049597499}, "descriptors": {"Citrus": {"min": 0, "max": 2.186886775508556, "mean": 0.28461734883184486, "median": 0.0, "std": 0.9511347133383555, "recipe_count": 120}, "Grapefruit": {"min": 0, "max": 2.687875968646896, "mean": 0.44976868747998383, "median": 0.0, "std": 1.1190536405834561, "recipe_count": 151}, "Orange": {"min": 0, "max": 1.5636912693647214, "mean": 0.20812200031533543, "median": 0.0, "std": 0.677784634524693, "recipe_count": 89}, "Lemon": {"min": 0, "max": 2.585126071184734, "mean": 0.4655609539278079, "median": 0.0, "std": 1.059782558628463, "recipe_count": 191}, "Melon": {"min": 0, "max": 2.004425319684369, "mean": 0.3011492000704294, "median": 0.0, "std": 0.8516380598069699, "recipe_count": 103}, "Apricot": {"min": 0, "max": 1.5588979497806956, "mean": 0.18579799139870984, "median": 0.0, "std": 0.6865499791909929, "recipe_count": 68}, "Peach": {"min": 0, "max": 1.4912686790794434, "mean": 0.17915529132009284, "median": 0.0, "std": 0.6560566938796752, "recipe_count": 67}, "Medium Intense": {"min": 0, "max": 1.3256955428571504, "mean": 0.10963837572827534, "median": 0.0, "std": 0.6080285835644376, "recipe_count": 48}, "Floral": {"min": 0, "max": 2.4316126412901875, "mean": 0.5878616433427944, "median": 0.21750227214874449, "std": 0.9218754989736966, "recipe_count": 372}, "Spicy": {"min": 0, "max": 1.683171378735722, "mean": 0.2819917330309122, "median": 0.0, "std": 0.700589822852405, "recipe_count": 178}, "Lime": {"min": 0, "max": 2.1226076553683617, "mean": 0.2895284076949457, "median": 0.0, "std": 0.9165396238367081, "recipe_count": 91}, "Gooseberry": {"min": 0, "max": 1.5102988519739076, "mean": 0.18655969406379325, "median": 0.0, "std": 0.6618695789550572, "recipe_count": 80}, "Passion Fruit": {"min": 0, "max": 1.7701498725141585, "mean": 0.19662783773418263, "median": 0.0, "std": 0.7867610173899879, "recipe_count": 60}, "Earthy": {"min": 0, "max": 1.9505316374024608, "mean": 0.4333657000226047, "median": 0.0, "std": 0.758582968689928, "recipe_count": 304}, "Mild": {"min": 0, "max": 1.5298824647823661, "mean": 0.30850821992284033, "median": 0.0, "std": 0.6106871224297629, "recipe_count": 233}, "Noble": {"min": 0, "max": 1.0921965836924044, "mean": 0.10389277355237644, "median": 0.0, "std": 0.494151905070014, "recipe_count": 56}, "Herbal": {"min": 0, "max": 1.677435079229658, "mean": 0.33929060295195146, "median": 0.0, "std": 0.6690722381388533, "recipe_count": 252}, "Lavender": {"min": 0, "max": 0.9770975898516043, "mean": 0.11344146444278637, "median": 0.0, "std": 0.431828062704409, "recipe_count": 79}, "Honey": {"min": 0, "max": 0.9770975898516043, "mean": 0.11344146444278637, "median": 0.0, "std": 0.431828062704409, "recipe_count": 79}, "Thyme": {"min": 0, "max": 0.9770975898516043, "mean": 0.11344146444278637, "median": 0.0, "std": 0.431828062704409, "recipe_count": 79}}}, "recipe_count": 699}, "dryhop": {"ibu": {"min": 0, "max": 102.15547786982836, "mean": 37.72858282945948, "median": 28.932770868711653, "std": 32.21344752018444}, "amount": {"min": 0, "max": 3.6938622364942706, "mean": 1.7053274992277923, "median": 1.3636363636363635, "std": 0.9942673686332392}, "unique_hops": 1, "flavor": {"total": {"min": 0, "max": 25.195419480496234, "mean": 9.509316122740902, "median": 7.470050192851353, "std": 7.843051678877666}, "descriptors": {"Citrus": {"min": 0, "max": 5.169483447338038, "mean": 0.5911025865727657, "median": 0.0, "std": 2.2891904303826363, "recipe_count": 36}, "Grapefruit": {"min": 0, "max": 3.299673184844796, "mean": 0.7559531714188606, "median": 0.0, "std": 1.2718600067129677, "recipe_count": 80}, "Orange": {"min": 0, "max": 1.8924083401034846, "mean": 0.3335749510780431, "median": 0.0, "std": 0.7794166945127208, "recipe_count": 47}, "Lemon": {"min": 0, "max": 3.2991361880976675, "mean": 0.6723777068231255, "median": 0.0, "std": 1.313379240637271, "recipe_count": 84}, "Melon": {"min": 0, "max": 2.9603862412966206, "mean": 0.6115449222701265, "median": 0.0, "std": 1.1744206595132471, "recipe_count": 66}, "Apricot": {"min": 0, "max": 1.6612817331813896, "mean": 0.2827735167636553, "median": 0.0, "std": 0.6892541082088671, "recipe_count": 41}, "Peach": {"min": 0, "max": 1.6612817331813896, "mean": 0.2827735167636553, "median": 0.0, "std": 0.6892541082088671, "recipe_count": 41}, "Medium Intense": {"min": 0, "max": 0.8749558125316326, "mean": 0.0840920486566956, "median": 0.0, "std": 0.3954318819374685, "recipe_count": 13}, "Floral": {"min": 0, "max": 1.8873815527906508, "mean": 0.3887807171783813, "median": 0.0, "std": 0.7493004178061348, "recipe_count": 72}, "Spicy": {"min": 0, "max": 1.57412246346974, "mean": 0.23449940683762616, "median": 0.0, "std": 0.669811528316057, "recipe_count": 47}, "Lime": {"min": 0, "max": 3.6164869135747, "mean": 0.6303056060638035, "median": 0.0, "std": 1.4930906537554482, "recipe_count": 45}, "Gooseberry": {"min": 0, "max": 3.1763030410318334, "mean": 0.5724236934267496, "median": 0.0, "std": 1.301939673802542, "recipe_count": 55}, "Passion Fruit": {"min": 0, "max": 5.493677666572459, "mean": 0.7212068882920477, "median": 0.0, "std": 2.386235389140206, "recipe_count": 37}, "Earthy": {"min": 0, "max": 1.7229524939595449, "mean": 0.2607283848033956, "median": 0.0, "std": 0.7311120545780746, "recipe_count": 55}, "Mild": {"min": 0, "max": 1.3278679102319235, "mean": 0.18807410976447692, "median": 0.0, "std": 0.5698969002337233, "recipe_count": 36}, "Noble": {"min": 0, "max": 1.2740944978519988, "mean": 0.08174585808070035, "median": 0.0, "std": 0.5961743198856492, "recipe_count": 9}, "Herbal": {"min": 0, "max": 1.854000088247353, "mean": 0.24229329536915267, "median": 0.0, "std": 0.8058533964391001, "recipe_count": 40}, "Lavender": {"min": 0, "max": 0.8384672042859146, "mean": 0.09466446000882642, "median": 0.0, "std": 0.3719013721385441, "recipe_count": 25}, "Honey": {"min": 0, "max": 0.8384672042859146, "mean": 0.09466446000882642, "median": 0.0, "std": 0.3719013721385441, "recipe_count": 25}, "Thyme": {"min": 0, "max": 0.8384672042859146, "mean": 0.09466446000882642, "median": 0.0, "std": 0.3719013721385441, "recipe_count": 25}}}, "recipe_count": 235}}}}]